{
    "POSCAR": {
        "Atomes": "   Mo    C   Cl\n",
        "coordinate": "Direct\n",
        "unit_cell": {
            "a_vector": "3.341459057173995   6.737839868526211e-11   -4.506041579328619e-08\n",
            "b_vector": "-1.6707295284760113   2.8937882528849364   9.823997383752468e-08\n",
            "c_vector": "-3.6149830597054554e-07   7.013460305962277e-07   26.991041036282887\n"
        },
        "positions": {
            "Mo": [
                "0.33333336545300235   0.6666667251740588   0.16524675346456955\n",
                "0.6666666945391936   0.33333330328545957   0.2347532449439632\n"
            ],
            "C": [
                "-2.6604638543509824e-08   -9.6569466537963e-09   0.19999999964449564\n"
            ],
            "Cl": [
                "0.33333331635990704   0.6666666740827653   0.3005355224640262\n",
                "0.6666666500102562   0.3333333072601742   0.099464479482945\n"
            ]
        }
    },
    "Termo_data": {
        "Temperature (K)": [
            0,
            10,
            20,
            30,
            40,
            50,
            60,
            70,
            80,
            90,
            100,
            110,
            120,
            130,
            140,
            150,
            160,
            170,
            180,
            190,
            200,
            210,
            220,
            230,
            240,
            250,
            260,
            270,
            280,
            290,
            300,
            310,
            320,
            330,
            340,
            350,
            360,
            370,
            380,
            390,
            400,
            410,
            420,
            430,
            440,
            450,
            460,
            470,
            480,
            490,
            500,
            510,
            520,
            530,
            540,
            550,
            560,
            570,
            580,
            590,
            600,
            610,
            620,
            630,
            640,
            650,
            660,
            670,
            680,
            690,
            700,
            710,
            720,
            730,
            740,
            750,
            760,
            770,
            780,
            790,
            800,
            810,
            820,
            830,
            840,
            850,
            860,
            870,
            880,
            890,
            900,
            910,
            920,
            930,
            940,
            950,
            960,
            970,
            980,
            990,
            1000,
            1010,
            1020,
            1030,
            1040,
            1050,
            1060,
            1070,
            1080,
            1090,
            1100,
            1110,
            1120,
            1130,
            1140,
            1150,
            1160,
            1170,
            1180,
            1190,
            1200,
            1210,
            1220,
            1230,
            1240,
            1250,
            1260,
            1270,
            1280,
            1290,
            1300,
            1310,
            1320,
            1330,
            1340,
            1350,
            1360,
            1370,
            1380,
            1390,
            1400,
            1410,
            1420,
            1430,
            1440,
            1450,
            1460,
            1470,
            1480,
            1490,
            1500,
            1510,
            1520,
            1530,
            1540,
            1550,
            1560,
            1570,
            1580,
            1590,
            1600,
            1610,
            1620,
            1630,
            1640,
            1650,
            1660,
            1670,
            1680,
            1690,
            1700,
            1710,
            1720,
            1730,
            1740,
            1750,
            1760,
            1770,
            1780,
            1790,
            1800,
            1810,
            1820,
            1830,
            1840,
            1850,
            1860,
            1870,
            1880,
            1890,
            1900,
            1910,
            1920,
            1930,
            1940,
            1950,
            1960,
            1970
        ],
        "Gibbs_free(J/mole)": [
            -494217.2904671242,
            -494217.60636287666,
            -494219.62062913826,
            -494224.9156941589,
            -494235.5826757349,
            -494253.7334638274,
            -494281.14830690937,
            -494319.12306318124,
            -494368.47792595957,
            -494429.65300929005,
            -494502.81164524227,
            -494587.92678757006,
            -494684.8550106799,
            -494793.3756623071,
            -494913.2254238813,
            -495044.1189436159,
            -495185.7590760932,
            -495337.8485400354,
            -495500.0927721749,
            -495672.2031060549,
            -495853.9001199616,
            -496044.91377988725,
            -496244.9827525554,
            -496453.8564401411,
            -496671.29396447336,
            -496897.0645930274,
            -497130.94615284057,
            -497372.72646132734,
            -497622.2015896875,
            -497879.17642073345,
            -498143.4639562581,
            -498414.8839100175,
            -498693.264428986,
            -498978.44055973896,
            -499270.25351488765,
            -499568.55163134186,
            -499873.18753051903,
            -500184.0216632223,
            -500500.9183240627,
            -500823.7486368032,
            -501152.38666882686,
            -501486.7126309978,
            -501826.6102713442,
            -502171.96840787283,
            -502522.67918591737,
            -502878.6392370645,
            -503239.7480779898,
            -503605.90896713064,
            -503977.0293022231,
            -504353.0187458945,
            -504733.78928462625,
            -505119.2576783709,
            -505509.3420199043,
            -505903.9638477465,
            -506303.0463578669,
            -506706.5156512775,
            -507114.30032345187,
            -507526.3306111409,
            -507942.53924131795,
            -508362.8608613341,
            -508787.2322651061,
            -509215.59161343955,
            -509647.878897289,
            -510084.0365084856,
            -510524.00745144964,
            -510967.73715638695,
            -511415.17222115776,
            -511866.2605990661,
            -512320.95155849605,
            -512779.19575705763,
            -513240.94608274347,
            -513706.1546811363,
            -514174.7767964667,
            -514646.7678443639,
            -515122.0846308493,
            -515600.6847455777,
            -516082.52749404224,
            -516567.57239129255,
            -517055.77997302206,
            -517547.11247926595,
            -518041.5325442856,
            -518539.0033047865,
            -519039.48910262773,
            -519542.95523841446,
            -520049.36774415226,
            -520558.69274890923,
            -521070.89826849813,
            -521585.9522852347,
            -522103.82330172375,
            -522624.4811408191,
            -523147.89588318084,
            -523674.0379771533,
            -524202.8787969892,
            -524734.3906143645,
            -525268.5456738226,
            -525805.3172628977,
            -526344.6784682132,
            -526886.6040148059,
            -527431.0681141994,
            -527978.0459305902,
            -528527.513299218,
            -529079.4458967423,
            -529633.8207280696,
            -530190.6141707024,
            -530749.8040149206,
            -531311.3679207795,
            -531875.2840306202,
            -532441.5311003126,
            -533010.0878968455,
            -533580.9339467315,
            -534154.0487375018,
            -534729.4125520766,
            -535307.0058201634,
            -535886.8090162805,
            -536468.803236519,
            -537052.9704770291,
            -537639.2916171347,
            -538227.7491047845,
            -538818.3252886678,
            -539411.0024901293,
            -540005.7640340376,
            -540602.5925645275,
            -541201.4718692598,
            -541802.3854966155,
            -542405.3174172353,
            -543010.2518258815,
            -543617.1730975561,
            -544226.0660934887,
            -544836.9155468458,
            -545449.7065986296,
            -546064.42477786,
            -546681.0556321406,
            -547299.5847592867,
            -547919.9984477895,
            -548542.2827387803,
            -549166.4242211937,
            -549792.4092658535,
            -550420.2247988635,
            -551049.8579122953,
            -551681.2956911364,
            -552314.5254082894,
            -552949.5347257494,
            -553586.3113346994,
            -554224.8430306409,
            -554865.1178543593,
            -555507.1242001152,
            -556150.8502293697,
            -556796.284586248,
            -557443.4157854011,
            -558092.2327252533,
            -558742.7245722275,
            -559394.880137699,
            -560048.6888495963,
            -560704.1400645908,
            -561361.2233646607,
            -562019.9282939609,
            -562680.2447240275,
            -563342.16256387,
            -564005.6719358065,
            -564670.7628928329,
            -565337.425772571,
            -566005.651075435,
            -566675.4292580673,
            -567346.7509236755,
            -568019.6068933639,
            -568693.9881210206,
            -569369.8854564341,
            -570047.289977254,
            -570726.1929688192,
            -571406.5857036725,
            -572088.4595823189,
            -572771.8060698997,
            -573456.616782811,
            -574142.8833911563,
            -574830.5977449432,
            -575519.7516763107,
            -576210.3371627558,
            -576902.3463003375,
            -577595.771209732,
            -578290.6042851935,
            -578986.8375879113,
            -579684.4636520538,
            -580383.4749653273,
            -581083.8641192055,
            -581785.6237737677,
            -582488.7466280985,
            -583193.2255427209,
            -583899.0533560817,
            -584606.2230834287,
            -585314.7277591376,
            -586024.5604604738,
            -586735.7144155117,
            -587448.1828319168,
            -588161.9590746721,
            -588877.0365196726,
            -589593.4086615299,
            -590311.0690188824,
            -591030.0111022643
        ],
        "Cp(J/mole.K)": [
            -0.0,
            0.16693849443254294,
            0.6815942291286774,
            1.6131328789735562,
            2.960358457785332,
            4.571478710662632,
            6.264598181357725,
            7.899560682121955,
            9.400820046500304,
            10.742362238519126,
            11.927411538737944,
            12.973151525677535,
            13.898114329122464,
            14.720682135826792,
            15.457133653672647,
            16.119868166533706,
            16.720017547928734,
            17.265612079975842,
            17.763143267232234,
            18.21915121109922,
            18.63764240356975,
            19.02179287129258,
            19.37571862828047,
            19.702658263665207,
            20.004585869552102,
            20.283572133521368,
            20.54211151181661,
            20.781961496661836,
            21.004850806563617,
            21.211709161507315,
            21.40357961799598,
            21.58309933899583,
            21.750890538981196,
            21.907398052193457,
            22.05319027027872,
            22.189090242827664,
            22.31710012106926,
            22.437671072935295,
            22.550673659436857,
            22.65609509839858,
            22.75525775318968,
            22.849077247384383,
            22.937577658632684,
            23.021181240426024,
            23.099975249171194,
            23.17376348374088,
            23.244181985047213,
            23.312057219819756,
            23.374509803764454,
            23.433213297928194,
            23.49094109362344,
            23.545727046391367,
            23.597083489951984,
            23.6454652559595,
            23.69199729018146,
            23.736839957003966,
            23.778933193557776,
            23.819288720002927,
            23.858453587014893,
            23.895740320603405,
            23.930412592075214,
            23.964067984398397,
            23.99697906554502,
            24.027810747052897,
            24.057944875955627,
            24.087041513936036,
            24.11403658977647,
            24.13962314826194,
            24.16581774552469,
            24.190996500308543,
            24.21333158262147,
            24.23627448928164,
            24.258817186974763,
            24.279321824907623,
            24.29980329905245,
            24.320145939454907,
            24.338269995082943,
            24.35595134770847,
            24.375179953226997,
            24.392706655626647,
            24.407974157249726,
            24.42374391745968,
            24.440270523872343,
            24.45507199865824,
            24.468953924824078,
            24.48430489022588,
            24.498194091458572,
            24.510769388153673,
            24.524606109235776,
            24.537257168404302,
            24.548247790386277,
            24.56044699512574,
            24.573114957607984,
            24.58457632363709,
            24.59490625925239,
            24.605245515456637,
            24.61644382970428,
            24.62627239989829,
            24.63607062920346,
            24.64617465994656,
            24.655609582550753,
            24.664977215422837,
            24.67343789837316,
            24.682601001212387,
            24.691495006531625,
            24.69975232197612,
            24.708203892997624,
            24.716108919549075,
            24.723830963729185,
            24.731443073952764,
            24.739665514469458,
            24.747058332918332,
            24.752934343228276,
            24.76111523908007,
            24.769248141394847,
            24.774355144298497,
            24.781343660433777,
            24.788665949334806,
            24.794967818202153,
            24.801649933674902,
            24.80726955737893,
            24.81364451169228,
            24.820023897447477,
            24.82569632225795,
            24.83141027028914,
            24.837307316192714,
            24.843322252010694,
            24.84830416952018,
            24.85370151884854,
            24.860003993671853,
            24.86493884021165,
            24.869636501447534,
            24.87539362065736,
            24.880834536478694,
            24.88563439192386,
            24.889964396672344,
            24.89520585320415,
            24.900827515262257,
            24.90503095553732,
            24.909294632007068,
            24.91450645553414,
            24.919177731513624,
            24.92310603727779,
            24.927990883874415,
            24.93307926161276,
            24.937160386762116,
            24.941110726782895,
            24.944991806678964,
            24.94995394115082,
            24.954793565074638,
            24.95808953448453,
            24.962242034618765,
            24.966903243237827,
            24.970756978878782,
            24.974350563745247,
            24.97840708890021,
            24.98282440812238,
            24.986781786187645,
            24.990168692468657,
            24.99421821591386,
            24.998594927136537,
            25.001954194451578,
            25.0053066913148,
            25.009697601347348,
            25.013803871884477,
            25.016717914099225,
            25.020139656606133,
            25.024408022818044,
            25.028224681550398,
            25.031603191810667,
            25.0349947176003,
            25.03848275076816,
            25.042175052500284,
            25.045918857615234,
            25.04928220945294,
            25.052732566983238,
            25.056368320343154,
            25.06037166935225,
            25.063873853219633,
            25.066184469376203,
            25.069496565498923,
            25.073478818143485,
            25.077011161063695,
            25.080340966778074,
            25.083618358500416,
            25.087013291907816,
            25.0903386592275,
            25.093880965088395,
            25.0972307850964,
            25.100396928235646,
            25.10372339055067,
            25.106963304653803,
            25.110318300873587,
            25.11377614009225,
            25.117235551808875,
            25.12016264835367,
            25.12322460613325,
            25.127170870030554
        ],
        "S(J/mole.K)": [
            0,
            0.08346924721627147,
            0.3373370517147123,
            0.7765910888258076,
            1.4154913758779002,
            2.24268405416733,
            3.22188177368007,
            4.30818595656383,
            5.459991543907382,
            6.644340698953602,
            7.8375091780304516,
            9.023568460679964,
            10.19234526343935,
            11.337613442633304,
            12.455834012411653,
            13.545203438927276,
            14.605032926184505,
            15.635345594556567,
            16.636578360867862,
            17.609450354840373,
            18.554842762590123,
            19.47368365294824,
            20.366940724768938,
            21.23561662422653,
            22.080697487747965,
            22.903131136034062,
            23.703843184700965,
            24.48373492952451,
            25.24367268989736,
            25.984478434917403,
            26.706923885358265,
            27.41176471779254,
            28.099736887931794,
            28.771524826121457,
            29.427766721261285,
            30.069065346351998,
            30.696012073724706,
            31.30918356888433,
            31.90911473039596,
            32.496296878323484,
            33.07120035791013,
            33.63428836332969,
            34.186002047532384,
            34.726756602188836,
            35.25694447488786,
            35.776930454558894,
            36.28707086750073,
            36.7877256282336,
            37.279210714077635,
            37.761809612607614,
            38.235833444951275,
            38.70158331712664,
            39.159318811923,
            39.609284272423245,
            40.05172504464572,
            40.48688484407976,
            40.91498620174825,
            41.33623923438499,
            41.75085668753381,
            42.15903928546322,
            42.5609656643006,
            42.95681255599193,
            43.34676336747143,
            43.730984302884465,
            44.10963390791876,
            44.48287153698475,
            44.85083856708443,
            45.21366710386646,
            45.57150338163555,
            45.9244902940889,
            46.27273973862539,
            46.616370096433826,
            46.95551209403784,
            47.29027282710886,
            47.62075741206573,
            47.94707957845749,
            48.269334082056595,
            48.58760980762454,
            48.90201648940274,
            49.212651862288475,
            49.51958592011069,
            49.822899609935845,
            50.1226895010579,
            50.419035251672895,
            50.712003497774994,
            51.00167735592549,
            51.288134039806025,
            51.57143189153939,
            51.85164273516929,
            52.128836847435736,
            52.40306576119983,
            52.67439242655309,
            52.94288947532841,
            53.20861415466642,
            53.47161326565546,
            53.731938527306184,
            53.98965046443918,
            54.24480065783864,
            54.49743444419582,
            54.74760431169561,
            54.99535798920405,
            55.24073988471791,
            55.48379195731104,
            55.72455863376526,
            55.963086195835785,
            56.19941317464399,
            56.433579174414625,
            56.665623142058024,
            56.89558115851832,
            57.123490325483715,
            57.34939033712725,
            57.57331659792688,
            57.79529400483589,
            58.0153606328211,
            58.23356014288292,
            58.44991178371856,
            58.664442507769856,
            58.87719311410619,
            59.08819100693363,
            59.29746304305881,
            59.50503527938126,
            59.7109346236597,
            59.91519175419817,
            60.11783062833857,
            60.31887474737887,
            60.518350630959326,
            60.716284472335246,
            60.91269705361774,
            61.10760979434708,
            61.30105117053172,
            61.49304215531302,
            61.68359881219076,
            61.87274606474966,
            62.06050801252714,
            62.24690182921477,
            62.43194372728176,
            62.61565527271014,
            62.79806069735496,
            62.97917524929654,
            63.15901264795248,
            63.337594807402645,
            63.514941066081526,
            63.69106436018629,
            63.86598258309678,
            64.03971658226365,
            64.21227998237447,
            64.38368495336763,
            64.55394662703766,
            64.72308392288105,
            64.89111522582098,
            65.05804977560621,
            65.22389983796603,
            65.38868423973909,
            65.55241599191068,
            65.7151053266658,
            65.87676638718258,
            66.03741504907521,
            66.19706394240202,
            66.35572249289254,
            66.51340347570077,
            66.67012225533836,
            66.82588868496532,
            66.98071137794904,
            67.13460511426092,
            67.28758357523911,
            67.43965340851281,
            67.59082351105171,
            67.7411087548011,
            67.89052089604812,
            68.03906765759021,
            68.18675799260382,
            68.33360226787627,
            68.47961122624547,
            68.62479529546835,
            68.76916304019396,
            68.9127229721038,
            69.0554850725559,
            69.19745994746772,
            69.33865609787026,
            69.47907751296151,
            69.61873227847536,
            69.75763352257636,
            69.89579016402276,
            70.03320857359503,
            70.16989610177116,
            70.3058608468069,
            70.4411107323671,
            70.57565381770982,
            70.70949771033483,
            70.84264883102733,
            70.97511442747927,
            71.10690189228335,
            71.23801838102081,
            71.36847143114719,
            71.4982681705398,
            71.62741398717189,
            71.75591451931832,
            71.88377892336285
        ]
    },
    "Phonon_data": {
        "Numb_Node": 15,
        "total_n_kpoints": 100,
        "frequency": {
            "Node_1": [
                -0.06964574544938198,
                -0.22026415810725913,
                -0.3988131460508283,
                -0.5138043764365412,
                -0.5129814385393677,
                -0.2069315023894603,
                0.7164423946042772,
                1.2322999172565734,
                1.7552019518409823,
                2.302052980650359,
                2.8745547728799132,
                3.4705773994391,
                4.086521503928625,
                4.718102355586978,
                5.3606966906206095,
                6.009499145850795,
                6.659531909111855,
                7.305447528327332,
                7.9407915075909035,
                8.554879645675834,
                9.117305750949702,
                9.580984550258538,
                9.988563908621053,
                10.37842945690007,
                10.760216313472213,
                11.137155782800626,
                11.510709830946752,
                11.881514062349899,
                12.249548055326825,
                12.61312081395412,
                12.933628092113885,
                13.037840357556675,
                13.081195317515018,
                13.098930026442382,
                13.102045321022675,
                13.09857678554291,
                13.094224490221,
                13.09239606973263,
                13.093043825894611,
                13.094977763814924,
                13.098172372800006,
                13.102592690470614,
                13.108203319261385,
                13.114977009858814,
                13.122899912704133,
                13.13197063928982,
                13.142184664690836,
                13.04469901827225,
                12.75751237654609,
                12.482829371324367,
                12.223951659094455,
                11.983886767744401,
                11.76542647466354,
                11.571169007297698,
                11.403506530484732,
                11.26457750306055,
                11.156186014870963,
                11.079695085187042,
                11.035904321313968,
                11.024920016628704,
                11.046012042534834,
                11.097416582284056,
                11.175960615954926,
                11.27617512496294,
                11.388022220270393,
                11.491407838313657,
                11.545413044823011,
                11.412071149985742,
                11.20840079633634,
                11.010818011360259,
                10.846543597993893,
                10.725719714227068,
                10.6499485463282,
                10.614393567948195,
                10.608661758804901,
                10.61782457751504,
                10.62400514958982,
                10.608577946366074,
                10.554665033491224,
                10.449233957886529,
                10.283879890233997,
                10.05296377591823,
                9.741429003904862,
                9.262006886733406,
                8.605502260840453,
                7.8914766748722025,
                7.152053038385521,
                6.399348219355838,
                5.64223894699369,
                4.888740217281253,
                4.1465140168918255,
                3.4229018162485043,
                2.724679083943702,
                2.0573969088015653,
                1.4233032929493137,
                0.8106271143620029,
                -0.20533056563330015,
                -0.5113782305181449,
                -0.4520233096327846,
                -0.26054002564409806,
                -0.06964574544938198
            ],
            "Node_2": [
                -0.055822469160786176,
                0.4974729370972179,
                0.9966205405819389,
                1.489832135135563,
                1.976764668697758,
                2.4576639130355726,
                2.933641885811134,
                3.4062898840405538,
                3.877163253573819,
                4.3473407932388755,
                4.817169399343032,
                5.286218324747838,
                5.753402440559865,
                6.217206330087311,
                6.675948211216336,
                7.128050571701474,
                7.57232314872375,
                8.008334511327716,
                8.437210715323516,
                8.864704389110859,
                9.316519963860483,
                9.835011164854464,
                10.37247352370607,
                10.88491040692396,
                11.356499570740272,
                11.777587018243072,
                12.140856852942957,
                12.44159419295475,
                12.678799353972595,
                12.857039016232397,
                13.021636600457395,
                13.35540966938854,
                13.713870108132445,
                14.072541634847756,
                14.429625039325556,
                14.78309143366413,
                15.124006574350746,
                15.34988811514289,
                15.307645372118653,
                15.188517741777092,
                15.007701614780673,
                14.780408054023805,
                14.520073408704608,
                14.237865086034619,
                13.942736956854768,
                13.641824998173707,
                13.340915590472212,
                13.15365326416032,
                13.16612351839014,
                13.17965687763422,
                13.194034778036842,
                13.208922807455224,
                13.223784478371442,
                13.237793361227643,
                13.249701433723457,
                13.257631485882335,
                13.258754792085478,
                13.248850218588471,
                13.221942669534611,
                13.170780936126066,
                13.08939702403893,
                12.977227453649924,
                12.840882780106599,
                12.69221207253764,
                12.547276698253885,
                12.43057015468469,
                12.402921780572782,
                12.627152959622837,
                12.988385515575374,
                13.407812135089603,
                13.795952076838798,
                13.782560434550291,
                13.690434891310803,
                13.560022656788318,
                13.387838179547343,
                13.168531505470591,
                12.89654250253893,
                12.566960619519591,
                12.176495919071709,
                11.724452763039897,
                11.213567040849172,
                10.65152338864333,
                10.061272420519535,
                9.541466640386952,
                9.114227491572192,
                8.673312441610092,
                8.199883090039016,
                7.695069407175039,
                7.163304286454094,
                6.609914375686139,
                6.0403331166194745,
                5.459529900561077,
                4.871494035875969,
                4.278837357384733,
                3.6826301857263477,
                3.082571490379931,
                2.4775199853167376,
                1.8662806383201007,
                1.2483808783448003,
                0.6242810455390685,
                -0.055822469160786176
            ],
            "Node_3": [
                -0.03942221658017246,
                1.055269432346364,
                2.1074034909827155,
                3.1482683195751617,
                4.173952902269598,
                5.181154484772421,
                6.167337725468351,
                7.130450792098287,
                8.068492223648276,
                8.979067095656756,
                9.859051603573532,
                10.704459449543917,
                11.510566959233147,
                12.272306073108462,
                12.984871627900644,
                13.644417441431631,
                14.248663135927579,
                14.797242457445673,
                15.291711056758507,
                15.735258226463213,
                16.13226152118835,
                16.487841514101373,
                16.807526027249676,
                17.097053899959295,
                17.362258182734355,
                17.608859076798726,
                17.841777871994832,
                18.061935454237542,
                18.207841326316125,
                18.090019440480642,
                17.863709342561613,
                17.583065487637697,
                17.27117102052788,
                16.941054340030323,
                16.600665919842314,
                16.256384102084446,
                15.919931684086833,
                15.69536683822075,
                15.69766359344541,
                15.701307595846906,
                15.702127981796837,
                15.698369796065668,
                15.68909830664465,
                15.673266245075736,
                15.64961658069729,
                15.616812960436343,
                15.573592700775487,
                15.518894555697496,
                15.451950410677123,
                15.372340614305603,
                15.280019853611183,
                15.175327209594462,
                15.058999797392149,
                14.932214436881507,
                14.796687558862612,
                14.654871065659773,
                14.51028504177775,
                14.367990351163213,
                14.235002128857088,
                14.119887372595702,
                14.03032069420357,
                13.969164867367065,
                13.933113481196385,
                13.915574539009212,
                13.910043160745735,
                13.911441232493125,
                13.91942016321886,
                13.925309749682805,
                13.922280702832913,
                13.90684293064458,
                13.933367765566455,
                14.35098074517494,
                14.82006842400096,
                15.284589802960678,
                15.732203859565093,
                16.151244324259785,
                16.528373623788593,
                16.847374338170102,
                17.08857752809096,
                17.230023149669737,
                17.25181507007594,
                17.142888521163176,
                16.90516540329648,
                16.550795854797848,
                16.095010513754264,
                15.55016994917284,
                14.923670517141382,
                14.21904204582229,
                13.438359949019668,
                12.584402358840515,
                11.661732811375606,
                10.676600820933755,
                9.636070748637877,
                8.546986270149665,
                7.415267093174957,
                6.245776845229608,
                5.042743882072877,
                3.810520088952413,
                2.554336279525279,
                1.2805441366168233,
                -0.03942221658017246
            ],
            "Node_4": [
                12.64763993602681,
                12.667938563751013,
                12.724945465240916,
                12.818632473975057,
                12.947270525756977,
                13.108485302335188,
                13.299392290623782,
                13.516713577414732,
                13.756896680457164,
                14.016227856067953,
                14.29093252740864,
                14.577259298308347,
                14.871548800538223,
                15.170292753750502,
                15.470190452256498,
                15.76820754228621,
                16.061633941199375,
                16.348125294362266,
                16.625701856973976,
                16.892679430540213,
                17.14752122348474,
                17.38861347388699,
                17.613957417411125,
                17.820716527873085,
                18.004449464223917,
                18.157705298578904,
                18.267753986458136,
                18.31637589902993,
                18.342112616450486,
                18.526096993225174,
                18.730563676341177,
                18.925222237102258,
                19.101981512209804,
                19.25461318446856,
                19.378142157665692,
                19.468867036747273,
                19.524270889116917,
                19.54289774362613,
                19.57211232489925,
                19.651209809781946,
                19.76045539661629,
                19.88439808983218,
                20.01957136600834,
                20.167335796439573,
                20.328133297451974,
                20.50073675477481,
                20.682796864295582,
                20.871367922835322,
                21.063327976323666,
                21.255762371829015,
                21.446315687988417,
                21.633446785932524,
                21.816513035410658,
                21.99566961491724,
                22.171642160950118,
                22.34546129472557,
                22.518229299308526,
                22.690949472816012,
                22.864414740800367,
                23.039133983031927,
                23.215266683503437,
                23.392524725054827,
                23.5699518319326,
                23.745239604515394,
                23.91084496854923,
                23.986683821911626,
                23.75578031839061,
                23.45990736472683,
                23.135327147351116,
                22.78999332882684,
                22.43050904429668,
                22.063982830647518,
                21.698644683026927,
                21.34405177607649,
                21.010830797135693,
                20.709611819007414,
                20.44855731246647,
                20.22874552717454,
                20.037383519381066,
                19.84294597322144,
                19.481919303208816,
                19.02689041768136,
                18.576655292641142,
                18.131498411465376,
                17.6892188362729,
                17.24732298657854,
                16.80469410671048,
                16.362212186909726,
                15.922546111900987,
                15.489656529732319,
                15.06833475036199,
                14.663872125960394,
                14.281836907993885,
                13.927902335104392,
                13.607678852980754,
                13.326525936393764,
                13.089342299268658,
                12.900354482526813,
                12.762937782928125,
                12.679478807716706,
                12.64763993602681
            ],
            "Node_5": [
                12.653007834389745,
                12.723241340558133,
                12.933485551862661,
                13.2716608214121,
                13.721912218741377,
                14.266122052338368,
                14.885625075058082,
                15.559168644884434,
                15.948308966856919,
                16.121503766854318,
                16.29911324677378,
                16.482262728673998,
                16.67107252555607,
                16.866011068541823,
                17.06773474566621,
                17.276778362787944,
                17.493240535476346,
                17.71653340311632,
                17.945251662758146,
                18.17719558866647,
                18.409545712114838,
                18.63914452532541,
                18.862814808664623,
                19.07764648655936,
                19.281205578673806,
                19.471636686874163,
                19.647552748560617,
                19.778810406694582,
                19.657174368279897,
                19.610181402516275,
                19.623897190921603,
                19.66973561391863,
                19.7269683431095,
                19.783442091445448,
                19.83223559991833,
                19.869327194998846,
                19.892389312955327,
                19.90020323146376,
                19.92548504762046,
                20.004890092703732,
                20.14515080563433,
                20.34446760930294,
                20.58517485891121,
                20.81355047008999,
                20.95813034551066,
                21.09226137516284,
                21.24118931707347,
                21.40833130788638,
                21.594114937435123,
                21.79795402986579,
                22.01860973533325,
                22.254308201980194,
                22.502809918365962,
                22.761437830729164,
                23.027016381409474,
                23.295642303254166,
                23.562140288821542,
                23.818898540296413,
                24.05358116815195,
                24.245980233546977,
                24.36990775865252,
                24.410682720277357,
                24.37925562542839,
                24.298072752001275,
                24.18886948028534,
                24.136861670681313,
                24.3238092783682,
                24.401119765539857,
                24.27485701839836,
                24.017609258899633,
                23.697504801270625,
                23.34261156024043,
                22.964813419984107,
                22.56972860138561,
                22.16009356458423,
                21.737259980895704,
                21.30219967625599,
                20.85637461381421,
                20.402398279982954,
                19.945098079702657,
                19.617799482836947,
                19.34085924658032,
                19.031368368667177,
                18.706671250054253,
                18.379402093195,
                18.05727463189678,
                17.744853435422563,
                17.444754319506476,
                17.158303438964047,
                16.88593664320084,
                16.62749684816255,
                16.38241255838143,
                16.149328802912304,
                15.921922351597686,
                15.622106737222184,
                14.931794538532568,
                14.194018506190634,
                13.557886555460824,
                13.06704702372104,
                12.755919093170805,
                12.653007834389745
            ],
            "Node_6": [
                15.164048359349794,
                15.179226822697736,
                15.22288756562952,
                15.293923872343578,
                15.389892798196168,
                15.50771333968417,
                15.64417688051295,
                15.7993672510924,
                16.29147623075467,
                17.02995542366451,
                17.751106816947235,
                18.36170670366218,
                18.907485691299836,
                19.455736856091633,
                20.01767107466304,
                20.59067954253659,
                21.162345067001702,
                21.693238908307496,
                22.04394159280005,
                21.897660865657055,
                21.6305040716425,
                21.35476609139066,
                21.0730223423822,
                20.78860678704956,
                20.506523396062423,
                20.234928077766067,
                19.987868023846474,
                19.817168816903134,
                19.956848532012835,
                20.0880059253419,
                20.204522963667777,
                20.30628300012933,
                20.39317659303444,
                20.465004646129678,
                20.52147125874536,
                20.562208437968312,
                20.586842300854837,
                20.59508905567019,
                20.60267606650813,
                20.625669171711095,
                20.664835471162007,
                20.721918466304892,
                20.80258905491094,
                20.945102800463992,
                21.207611233501662,
                21.5057113721791,
                21.804396827516456,
                22.091816252983918,
                22.36190959000558,
                22.614082266395265,
                22.85227707574115,
                23.081975895727226,
                23.307456887237013,
                23.53074142559107,
                23.751770087322335,
                23.96897940046167,
                24.179841970901848,
                24.38130036918618,
                24.570336525691577,
                24.74510159480502,
                24.90521917030835,
                25.046800444945283,
                25.15974318081179,
                25.235512872141936,
                25.271365258919875,
                25.270842478101414,
                25.229137853890744,
                25.240826349289343,
                25.361468059135124,
                25.084966958679438,
                24.68804073410741,
                24.274782636953628,
                23.852202621322306,
                23.42536547975745,
                22.999814956355994,
                22.58253186119577,
                22.183314493637464,
                21.817431286472537,
                21.50987605750833,
                21.297014672340538,
                21.21193481905425,
                21.257308792439044,
                21.40608723754042,
                21.623879454586987,
                21.87837204874426,
                22.097403162534448,
                21.602888011060625,
                20.91982307415847,
                20.237093926716636,
                19.568783582436424,
                18.92165483735312,
                18.295318880016854,
                17.609588361546194,
                16.735233963706886,
                15.950598335251705,
                15.628643986588708,
                15.46028117555014,
                15.332580065345974,
                15.239878958747687,
                15.183300612818826,
                15.164048359349794
            ],
            "Node_7": [
                15.164550777686951,
                15.197395760598726,
                15.296418757425332,
                15.458683845496479,
                15.680299072944008,
                15.956362823212972,
                16.28151371901283,
                16.65067268284184,
                17.06025851822247,
                17.511767117624927,
                18.031473534306752,
                18.697742306005694,
                19.45361517510906,
                20.22156489202934,
                20.97900094510104,
                21.710623515336014,
                22.376597229672157,
                22.402620870923062,
                22.15785935224739,
                22.07644741651041,
                21.94897113497429,
                21.78382510385862,
                21.617553574025003,
                21.466703093979998,
                21.34229277214718,
                21.252854493225325,
                21.20479783746492,
                21.202090943102856,
                21.24594108295104,
                21.334710505108774,
                21.463973826673833,
                21.626477790928305,
                21.811895320086453,
                22.006480686864087,
                22.19285121218476,
                22.35035576167549,
                22.457120031248206,
                22.495108903645228,
                22.500975087832018,
                22.518770797945653,
                22.549108898011266,
                22.59308377746569,
                22.652385957467637,
                22.729468359329054,
                22.827747722284897,
                22.95174972639421,
                23.106913554921327,
                23.29850648605932,
                23.52932571440234,
                23.797376657738173,
                24.095879935108908,
                24.41571867536395,
                24.74780589348851,
                25.083795177505095,
                25.414688914343877,
                25.633351496140534,
                25.588530965722725,
                25.541913171890112,
                25.50948976753137,
                25.507530629391212,
                25.55580848906764,
                25.665071639131547,
                25.825274642495536,
                26.01123074162413,
                26.189015518287512,
                26.296228816352777,
                26.156393971565603,
                25.846347802909484,
                25.522476625237122,
                25.63048620781123,
                25.647460205785453,
                25.307741592296765,
                24.867095564096434,
                24.394710501944722,
                23.91785718762638,
                23.45642390534617,
                23.02806716772076,
                22.649981657574372,
                22.339417115047844,
                22.1126376538707,
                21.981274306813237,
                21.946877721457856,
                21.998370838588585,
                22.115806913010474,
                22.276068347278787,
                22.351368176314885,
                22.412942115829615,
                22.148871279828626,
                21.352772765471805,
                20.468293035700615,
                19.55099471877772,
                18.625025635225434,
                17.792080805889682,
                17.210562566978624,
                16.7081030261224,
                16.263800589273593,
                15.883711930307024,
                15.576332705889143,
                15.349892006628567,
                15.21110683097152,
                15.164550777686951
            ],
            "Node_8": [
                24.49273134460899,
                24.4870646861523,
                24.469260681808343,
                24.43588715379105,
                24.3857932176902,
                24.320252946091546,
                24.239631860910656,
                24.14402705503221,
                24.03353211390591,
                23.90829151400355,
                23.7685024755543,
                23.614398444418505,
                23.44622856340728,
                23.264244173678858,
                23.068704173687795,
                22.859929580712027,
                22.638998431403866,
                22.76625656208913,
                22.932339829885343,
                23.33815071908682,
                23.880058615561033,
                24.448150453545725,
                25.008157715707455,
                25.544734012249588,
                26.046768718474144,
                26.502053357681653,
                26.891446383573445,
                27.178007538474958,
                27.304581261730192,
                27.260633353472585,
                27.112468582032626,
                26.91652351664628,
                26.702044164180155,
                26.487610118614384,
                26.28996619060949,
                26.127240061528752,
                26.018626967976612,
                25.980249825846823,
                25.980323197291742,
                25.980476235998506,
                25.980510499083014,
                25.980104501865615,
                25.978827462409374,
                25.976158144165527,
                25.971508178780915,
                25.964248933541644,
                25.9537407813716,
                25.9393636926397,
                25.92054857081159,
                25.896809935287457,
                25.8677829047653,
                25.833272439033216,
                25.79333678543962,
                25.748491909663677,
                25.70085686378331,
                25.7509703859147,
                26.04316441725756,
                26.308583836654307,
                26.525958417554705,
                26.68133862663918,
                26.76984907846316,
                26.799855820377587,
                26.788071929681077,
                26.749504798421754,
                26.689177141807406,
                26.620378977579595,
                26.586341813991357,
                26.522909951002543,
                26.38373766237941,
                26.177648960017315,
                26.09882306139235,
                26.30347538419904,
                26.537026748520525,
                26.72824630882217,
                26.838218535739905,
                26.8368999712549,
                26.717190378142625,
                26.492676774175123,
                26.180566132754908,
                25.7934546486542,
                25.33987263097685,
                24.826607677438663,
                24.26055138898329,
                23.6501684247539,
                23.00874437380753,
                22.500024910424624,
                22.665478870326996,
                22.83174082917494,
                23.052079721437284,
                23.27128623550871,
                23.47382417146223,
                23.659777337362396,
                23.829260799627814,
                23.98157548003978,
                24.115733867603176,
                24.23074475584217,
                24.325710324487122,
                24.399812121540265,
                24.452270607220388,
                24.482845444322862,
                24.49273134460899
            ],
            "Node_9": [
                24.505167761258498,
                24.498283309912534,
                24.478479725957225,
                24.449298294635746,
                24.41198741906615,
                24.365262366314006,
                24.308553847430755,
                24.241326611689647,
                24.16283996088947,
                24.072196522756368,
                23.96852293894771,
                23.85125096842599,
                23.720514528470787,
                23.57778501108941,
                23.427264064477658,
                23.280546782806272,
                23.183219571447285,
                23.38323861269552,
                23.95504632834793,
                24.575833872999574,
                25.179057039264855,
                25.7519399297253,
                26.289300981676917,
                26.787822290523355,
                27.24477846246812,
                27.657046508713737,
                28.013507398701798,
                28.199799613285975,
                28.241346962966308,
                28.342615181472638,
                28.462508678110524,
                28.559167494440867,
                28.623414913647455,
                28.660268338169402,
                28.6781952165654,
                28.685058102568956,
                28.68677593976982,
                28.686947809644504,
                28.68586400427134,
                28.68258719374954,
                28.677040355362625,
                28.669092419588527,
                28.658554570373244,
                28.64517575499301,
                28.628638086238993,
                28.608553017598084,
                28.584459377021386,
                28.555824535681126,
                28.522050110043693,
                28.48248356667467,
                28.43643683984923,
                28.383212536670143,
                28.32213746080233,
                28.25260187857704,
                28.174100682970842,
                28.086268690319685,
                27.988897692318385,
                27.88192502064977,
                27.765408518911958,
                27.639557459335403,
                27.50493988078401,
                27.363028518585658,
                27.217521581734488,
                27.0780781324689,
                26.96984664479741,
                26.93702842002808,
                27.092033543804313,
                27.376055381507992,
                27.667975662307843,
                27.932000477592126,
                28.153727532167533,
                28.320518431437783,
                28.400932321580495,
                28.389444870858128,
                28.37485191324616,
                28.354047051130422,
                28.248077071194032,
                28.04545932220523,
                27.76307033221686,
                27.407871936004256,
                26.98345434705705,
                26.492608695833805,
                25.938147942518157,
                25.323470874362947,
                24.653577220357448,
                23.939035050639447,
                23.23101945975132,
                22.98471709508954,
                23.165684958892648,
                23.377092058606447,
                23.581201454003264,
                23.76676512382004,
                23.929732530629725,
                24.069592536321537,
                24.187414879788246,
                24.284798659034127,
                24.363290992819056,
                24.424131182580073,
                24.46821632204095,
                24.495681824991333,
                24.505167761258498
            ],
            "Node_10": [
                26.950877321610776,
                26.958858171198223,
                26.982637916356985,
                27.021744407892022,
                27.07544138752915,
                27.142792965713973,
                27.222733669418872,
                27.31412898585641,
                27.415811975598807,
                27.526583735107504,
                27.645169264122256,
                27.770126016264314,
                27.89971034979248,
                28.031717147335463,
                28.163319667609514,
                28.29094954110831,
                28.41026880396906,
                28.516291861849474,
                28.60370517643675,
                28.667393293279464,
                28.703107869401567,
                28.708139451811192,
                28.681840297778162,
                28.62598429938096,
                28.54531928473401,
                28.449696275488368,
                28.366002310649467,
                28.443904028357252,
                28.715631838821867,
                28.99073271492405,
                29.251236248625656,
                29.49374672008793,
                29.71279731565212,
                29.902053939652532,
                30.055747417388904,
                30.169146624988834,
                30.238690373092762,
                30.262129688654433,
                30.256599800357403,
                30.240042766714524,
                30.212558726951432,
                30.174321473793018,
                30.125586932789535,
                30.066701991445527,
                29.998112024416624,
                29.920366532536615,
                29.834123952779684,
                29.74015864660807,
                29.639375115789747,
                29.532836597043403,
                29.421817688345186,
                29.307894465796345,
                29.193092295254168,
                29.080123416059216,
                28.97276413698506,
                28.876434922407284,
                28.799000055921603,
                28.751510370577336,
                28.747730345945445,
                28.800171877575668,
                28.91224105417579,
                29.07270225191527,
                29.25811035321509,
                29.437683866379377,
                29.574823402413745,
                29.632957431954324,
                29.537737633911384,
                29.30700266981592,
                29.05678256062761,
                28.844919655234573,
                28.687212261997555,
                28.580965952413138,
                28.540973616139382,
                28.566377571112653,
                28.57487807690998,
                28.577664879305683,
                28.644546796901633,
                28.76127982054903,
                28.88488230862709,
                28.989870676764752,
                29.061537944368713,
                29.091887679282163,
                29.077963370220278,
                29.02093146499992,
                28.925226742088768,
                28.79755969973625,
                28.64584650856446,
                28.478213177070284,
                28.302208271709883,
                28.1242973872848,
                27.94964959668068,
                27.782177485811676,
                27.624760747610807,
                27.47956783608917,
                27.348389439567438,
                27.23290930365148,
                27.134859490004533,
                27.056035969258044,
                26.998183747497798,
                26.962793651336582,
                26.950877321610776
            ],
            "Node_11": [
                34.997224263978666,
                34.9897486156812,
                34.96703831310366,
                34.92830553529856,
                34.8724349174735,
                34.79824704148008,
                34.704806278795196,
                34.591723131981006,
                34.45940167286902,
                34.3091916292391,
                34.14342098279402,
                33.96530575443196,
                33.77875460182395,
                33.588101757039055,
                33.39780798786368,
                33.21216330669223,
                33.03500912212473,
                32.86947959283997,
                32.71775645133929,
                32.58085444399358,
                32.458509167716386,
                32.34929475436847,
                32.251087612985444,
                32.16186180237071,
                32.08059696967086,
                32.00794116030848,
                31.946303879444255,
                31.899234568677805,
                31.87018376747778,
                31.8610141013883,
                31.870867986617224,
                31.89597780194944,
                31.930533139509517,
                31.968102805984355,
                32.00290959419233,
                32.03055066745856,
                32.04815279319861,
                32.05417779809872,
                32.052808313898836,
                32.048692727705685,
                32.04181263491524,
                32.03214674742334,
                32.019683001328495,
                32.004432008782395,
                31.986439285426652,
                31.965794028568915,
                31.942632996645166,
                31.917139046660658,
                31.889534884270997,
                31.860073356961678,
                31.829026033142455,
                31.7966718143113,
                31.763286976421025,
                31.729137460282843,
                31.694473599363597,
                31.659526948382325,
                31.624508563679708,
                31.58960800032163,
                31.554992312401943,
                31.52080407008505,
                31.487155380867414,
                31.454104165243056,
                31.421535543210577,
                31.38838241148463,
                31.34794892082461,
                31.307873038087987,
                31.271677295132477,
                31.2315667094953,
                31.19185208189421,
                31.155073461395922,
                31.122944941441716,
                31.097555645585683,
                31.08168030773691,
                31.078710886090036,
                31.09219456172618,
                31.125103531375725,
                31.17922996593889,
                31.255066691559886,
                31.352140309831018,
                31.46946882655083,
                31.60588782563312,
                31.760200778708086,
                31.931216137586468,
                32.117726754582876,
                32.31844773331676,
                32.53190616169581,
                32.756279677734305,
                32.989203122453475,
                33.227590857629046,
                33.46754185070165,
                33.70439225188546,
                33.932950112333664,
                34.14789523018635,
                34.34427132532599,
                34.51795946566465,
                34.66601664962145,
                34.78679471921278,
                34.87981228358539,
                34.94541790434075,
                34.984337099362236,
                34.997224263978666
            ],
            "Node_12": [
                41.93627736046449,
                41.91438855633699,
                41.84917184206772,
                41.74195936077106,
                41.594915719063316,
                41.41095763590923,
                41.19364774074625,
                40.94706884620776,
                40.67568651844972,
                40.38420867750431,
                40.07745112545141,
                39.760217364448714,
                39.437199992939796,
                39.11290942240742,
                38.79163338068304,
                38.477427022168186,
                38.174127661921894,
                37.885379783876814,
                37.61464582407887,
                37.365169303567704,
                37.13985538013493,
                36.941048755957205,
                36.770227174052174,
                36.62768501863967,
                36.51232800982507,
                36.42169540442581,
                36.35225186193919,
                36.29988249079497,
                36.260449583797744,
                36.23026844268497,
                36.206415550654754,
                36.186849899482986,
                36.17037551049618,
                36.156494022199325,
                36.14519892811122,
                36.13675679785939,
                36.131510620250666,
                36.12972859930613,
                36.120441481455416,
                36.0926463341559,
                36.04653765327542,
                35.98242657640171,
                35.90072370549192,
                35.80191922116637,
                35.686563335626495,
                35.55524976807982,
                35.4086041213557,
                35.24727801702287,
                35.0719488528442,
                34.8833242967505,
                34.68215028644424,
                34.469221459803215,
                34.24539364086478,
                34.01159927203897,
                33.76886858416444,
                33.51836205844533,
                33.26142394222749,
                32.99967358407824,
                32.73516417020979,
                32.47066377323144,
                32.210166133137385,
                31.959848555585005,
                31.729916203269266,
                31.538259871155116,
                31.41789715525691,
                31.391782239703495,
                31.537702368355156,
                31.860680711716352,
                32.251305151595254,
                32.65635935350198,
                33.05316217310214,
                33.43133992264623,
                33.78610338157744,
                34.11573457602341,
                34.42058635001831,
                34.702678495937924,
                34.96553041019418,
                35.21404074382985,
                35.45427980710012,
                35.69310076015427,
                35.93754462241267,
                36.19411418010567,
                36.46808026605283,
                36.76299826408627,
                37.080530308527,
                37.42054094017348,
                37.78134466358287,
                38.159974831746766,
                38.5523930869589,
                38.95362064433295,
                39.3578158222896,
                39.75833972180415,
                40.147850676583886,
                40.51845697111259,
                40.8619425255168,
                41.17006503629401,
                41.43491214362274,
                41.64928983382711,
                41.80710968675793,
                41.903738681417536,
                41.93627736046449
            ],
            "Node_13": [
                63.62655518422551,
                63.61084195771103,
                63.56398740106471,
                63.48684931555987,
                63.38086379295749,
                63.248049395033945,
                63.091003517249234,
                62.91288421630861,
                62.717371713289594,
                62.50860556910333,
                62.29109574627475,
                62.06960814112147,
                61.84902755827342,
                61.63420342606209,
                61.429785701190504,
                61.240060188471375,
                61.068793639846504,
                60.91909920619583,
                60.79333185361234,
                60.69302112017606,
                60.618845209718955,
                60.57064631399337,
                60.54748289977717,
                60.54771128331766,
                60.56908682300224,
                60.608874846962145,
                60.66396290796328,
                60.73096863459357,
                60.80634060456837,
                60.88645256122759,
                60.96769333198586,
                61.0465556241758,
                61.11972636511519,
                61.18417957536096,
                61.237270319021036,
                61.27682565984719,
                61.30122644867719,
                61.30947278095742,
                61.3075462762888,
                61.30181288073017,
                61.29240999568559,
                61.279563373561174,
                61.263582023289295,
                61.24485072588294,
                61.223819988499834,
                61.20099342115896,
                61.1769127476951,
                61.152140911119645,
                61.12724394400576,
                61.1027723966496,
                61.079243124028636,
                61.05712213422577,
                61.03680903432623,
                61.01862343308296,
                61.00279353322396,
                60.989447112293114,
                60.978605156608275,
                60.9701785437707,
                60.96396829634231,
                60.959669970861434,
                60.9568826354938,
                60.955122599944985,
                60.95384161996012,
                60.95244878332829,
                60.950334804756196,
                60.94689712848283,
                60.93720503282076,
                60.920678049298154,
                60.8957814739989,
                60.86162509446628,
                60.81805844585725,
                60.76571490120987,
                60.706007240368656,
                60.64108001629398,
                60.57372572719876,
                60.50727292343305,
                60.44545501025901,
                60.39226830492499,
                60.35182634790652,
                60.328214310117666,
                60.32534300655437,
                60.346797751167635,
                60.39567489383994,
                60.47440024931888,
                60.58452987544852,
                60.72654424175169,
                60.89965904236543,
                61.10168531431394,
                61.32897354345037,
                61.57646852412661,
                61.83788493497971,
                62.105992473482644,
                62.37298020000258,
                62.63085777772692,
                62.8718489709055,
                63.08873925954752,
                63.275151808088694,
                63.42574086329848,
                63.53630611471074,
                63.60384347242789,
                63.62655518422551
            ],
            "Node_14": [
                76.87374276424254,
                76.87490081378367,
                76.87806247758208,
                76.88234564859174,
                76.88645347611748,
                76.88890091680304,
                76.888278898285,
                76.88352158830199,
                76.8741422674961,
                76.8604039967922,
                76.84339573825223,
                76.82499422494513,
                76.80770500478995,
                76.79438907278912,
                76.78789079061458,
                76.7905887495878,
                76.80390903336021,
                76.82791974016726,
                76.86130901063358,
                76.90206430572202,
                76.94844899777019,
                76.99929438238844,
                77.05362057464147,
                77.1103495071005,
                77.16833394842726,
                77.22650789946039,
                77.28399863077533,
                77.3401501287436,
                77.39446623987311,
                77.44650492680552,
                77.49576165130955,
                77.54157716850206,
                77.58309574344466,
                77.61928627161701,
                77.64902370049948,
                77.67121442843002,
                77.68493961884948,
                77.68958642483618,
                77.69965683027387,
                77.7296581653285,
                77.77897236506448,
                77.84660565924659,
                77.93123577722976,
                78.03126540903895,
                78.14487328577759,
                78.27005605002485,
                78.40465706566262,
                78.54638120803622,
                78.69279605388348,
                78.84131851877443,
                78.98918153205328,
                79.13337109338364,
                79.27053782528138,
                79.39698099037844,
                79.50907452815964,
                79.60464052165514,
                79.68448945493365,
                79.75188003921414,
                79.8103251297955,
                79.86227326995325,
                79.90902731850383,
                79.95104793725075,
                79.98820653941976,
                80.01991516300703,
                80.04514088954842,
                80.06229660423742,
                80.06643761737435,
                80.02865664122656,
                79.93605401936705,
                79.79203450973344,
                79.60770964761663,
                79.39223993593183,
                79.15283954320637,
                78.89609535609013,
                78.62859011345395,
                78.35706083493409,
                78.08830913789123,
                77.8289753198838,
                77.58525205506787,
                77.36260127209798,
                77.16552366076674,
                76.99740734478613,
                76.8604544522942,
                76.75566085085842,
                76.68281439346195,
                76.64048491007338,
                76.62600142523254,
                76.63543816520553,
                76.66364754653699,
                76.70437831011074,
                76.75052123618538,
                76.79463769535349,
                76.83028212362704,
                76.85436759139442,
                76.86817281065804,
                76.87489331449318,
                76.87721049929067,
                76.87698095474704,
                76.87562434923016,
                76.87428374039466,
                76.87374276424254
            ],
            "Node_15": [
                77.09397432551123,
                77.09661730919429,
                77.10407721390895,
                77.11501088516836,
                77.127389143739,
                77.13879280434352,
                77.14678135615259,
                77.14928133755275,
                77.14493433111802,
                77.13335066294721,
                77.11523173170136,
                77.09234736556215,
                77.06738089465777,
                77.0436803136442,
                77.02497563837584,
                77.01513468582685,
                77.01801418954909,
                77.03737083505185,
                77.07658781770667,
                77.13792339121491,
                77.22167362063882,
                77.32618728835784,
                77.4486524395315,
                77.58581417105897,
                77.73432693234541,
                77.89088074995654,
                78.05223275810516,
                78.21519632067475,
                78.3766091181822,
                78.53329779052616,
                78.68205774161574,
                78.8196645290242,
                78.94292690911965,
                79.04878265323377,
                79.13442892224226,
                79.19747132069021,
                79.23607117500724,
                79.24906976863456,
                79.25132270867087,
                79.25803516314743,
                79.26907591259798,
                79.28425063891942,
                79.30333246079573,
                79.32609438829698,
                79.35233706189862,
                79.38190737102207,
                79.4147073086494,
                79.45069695148321,
                79.48990002109471,
                79.53242463759803,
                79.57851523992619,
                79.62865134983711,
                79.68368853726528,
                79.74493655619578,
                79.81379352625848,
                79.8904181125729,
                79.9722104839769,
                80.0543453029427,
                80.13193359150809,
                80.20129395904218,
                80.25998576338964,
                80.30647057841598,
                80.3398476219228,
                80.35973906282301,
                80.3663130502092,
                80.3604414526632,
                80.32984775355648,
                80.28717941323407,
                80.24521400099118,
                80.20123066023264,
                80.14571094506391,
                80.07216964735572,
                79.97734407500266,
                79.86002116020425,
                79.72044463964355,
                79.56002613647439,
                79.38113801236754,
                79.18691416411475,
                78.98105404706052,
                78.76764786124022,
                78.55103772186872,
                78.3357129383664,
                78.12621803190105,
                77.92703998143146,
                77.74244374380541,
                77.5762443537298,
                77.43153548952998,
                77.31042879552182,
                77.21388380920648,
                77.14171190159864,
                77.09279048544047,
                77.06532990996138,
                77.05658281223457,
                77.06156485170987,
                77.0729660379277,
                77.08414621532262,
                77.09161460172975,
                77.09488072464221,
                77.09521065611933,
                77.09442102639879,
                77.09397432551123
            ]
        }
    },
    "Phonon_DOS": {
        "DOS": [
            0.0,
            0.0015555555555555555,
            0.0005925925925925926,
            0.0011851851851851852,
            0.003111111111111111,
            0.003111111111111111,
            0.004,
            0.00488888888888889,
            0.00488888888888889,
            0.006666666666666667,
            0.008148148148148147,
            0.00977777777777778,
            0.021629629629629627,
            0.020592592592592593,
            0.023333333333333334,
            0.034074074074074076,
            0.014518518518518517,
            0.022666666666666665,
            0.03037037037037037,
            0.029333333333333333,
            0.020296296296296295,
            0.02962962962962963,
            0.04318518518518519,
            0.055851851851851854,
            0.04496296296296297,
            0.036148148148148145,
            0.023555555555555555,
            0.01955555555555556,
            0.03392592592592592,
            0.0242962962962963,
            0.07370370370370372,
            0.01511111111111111,
            0.002,
            0.041185185185185186,
            0.016666666666666666,
            0.012444444444444444,
            0.01162962962962963,
            0.016666666666666666,
            0.01614814814814815,
            0.006518518518518518,
            0.004,
            0.0035555555555555557,
            0.0022222222222222222,
            0.0022962962962962967,
            0.0,
            0.0,
            0.0,
            0.0,
            0.0,
            0.0,
            0.0,
            0.0,
            0.0,
            0.0,
            0.0,
            0.0,
            0.0,
            0.0,
            0.0,
            0.0,
            0.0,
            0.0,
            0.04696296296296296,
            0.013703703703703702,
            0.004,
            0.002,
            0.0,
            0.0,
            0.0,
            0.0,
            0.0,
            0.0,
            0.0,
            0.0,
            0.0,
            0.0,
            0.0,
            0.0,
            0.02362962962962963,
            0.04622222222222223,
            0.026962962962962963,
            0.030444444444444444,
            0.006074074074074075,
            0.0
        ],
        "Energy(meV)": [
            -1.5,
            -0.5,
            0.5,
            1.5,
            2.5,
            3.5,
            4.5,
            5.5,
            6.5,
            7.5,
            8.5,
            9.5,
            10.5,
            11.5,
            12.5,
            13.5,
            14.5,
            15.5,
            16.5,
            17.5,
            18.5,
            19.5,
            20.5,
            21.5,
            22.5,
            23.5,
            24.5,
            25.5,
            26.5,
            27.5,
            28.5,
            29.5,
            30.5,
            31.5,
            32.5,
            33.5,
            34.5,
            35.5,
            36.5,
            37.5,
            38.5,
            39.5,
            40.5,
            41.5,
            42.5,
            43.5,
            44.5,
            45.5,
            46.5,
            47.5,
            48.5,
            49.5,
            50.5,
            51.5,
            52.5,
            53.5,
            54.5,
            55.5,
            56.5,
            57.5,
            58.5,
            59.5,
            60.5,
            61.5,
            62.5,
            63.5,
            64.5,
            65.5,
            66.5,
            67.5,
            68.5,
            69.5,
            70.5,
            71.5,
            72.5,
            73.5,
            74.5,
            75.5,
            76.5,
            77.5,
            78.5,
            79.5,
            80.5,
            81.5
        ]
    }
}